upsay_jupyter_ai/__init__.py
upsay_jupyter_ai/config.py
upsay_jupyter_ai/.ipynb_checkpoints/__init__-checkpoint.py
upsay_jupyter_ai/.ipynb_checkpoints/config-checkpoint.py
upsay_jupyter_ai-1.0.dist-info/LICENSE
upsay_jupyter_ai-1.0.dist-info/WHEEL
upsay_jupyter_ai-1.0.dist-info/METADATA
upsay_jupyter_ai-1.0.dist-info/RECORD
