Metadata-Version: 2.1
Name: upsay_jupyter_ai
Version: 1.0
Summary: Testing the deployment of UPSayAI, a Jupyter-integrated Generative AI toolkit for Université Paris-Saclay students.
Author-email: Paulo Couto <paulohenriquecrs@hotmail.com>
Classifier: License :: OSI Approved :: MIT License
Requires-Dist: transformers
Requires-Dist: ipython
Requires-Dist: torch
Requires-Dist: pandas
Requires-Dist: numpy
Requires-Dist: rank_bm25
Requires-Dist: nltk
Requires-Dist: huggingface_hub
Requires-Dist: ipywidgets
Requires-Dist: langchain_openai
Project-URL: Home, https://gitlab.dsi.universite-paris-saclay.fr/paulo.couto-de-resende-silva/upsayai
